LICENSE
MANIFEST.in
README.rst
setup.cfg
setup.py
pmatic/__init__.py
pmatic/api.py
pmatic/ccu.py
pmatic/entities.py
pmatic/events.py
pmatic/exceptions.py
pmatic/manager.py
pmatic/notify.py
pmatic/params.py
pmatic/residents.py
pmatic/utils.py
pmatic.egg-info/PKG-INFO
pmatic.egg-info/SOURCES.txt
pmatic.egg-info/dependency_links.txt
pmatic.egg-info/requires.txt
pmatic.egg-info/top_level.txt