Metadata-Version: 1.1
Name: pmatic
Version: 0.5
Summary: Python API for Homematic. Easy to use.
Home-page: https://larsmichelsen.github.io/pmatic/
Author: Lars Michelsen
Author-email: lm@larsmichelsen.com
License: GPLv2
Download-URL: https://pypi.python.org/pypi/pmatic
Keywords: Homematic,Python,CCU,Automating,Scripting,Home Automation
Platform: Linux
Platform: Windows
Platform: OS X
Platform: CCU2
Classifier: Development Status :: 4 - Beta
Classifier: Environment :: Console
Classifier: Intended Audience :: Developers
Classifier: Intended Audience :: System Administrators
Classifier: License :: OSI Approved :: GNU General Public License v2 (GPLv2)
Classifier: Operating System :: OS Independent
Classifier: Operating System :: POSIX
Classifier: Operating System :: Microsoft :: Windows
Classifier: Operating System :: MacOS :: MacOS X
Classifier: Programming Language :: Python
Classifier: Programming Language :: Python :: 2.7
Classifier: Programming Language :: Python :: 3
Classifier: Programming Language :: Python :: 3.2
Classifier: Programming Language :: Python :: 3.3
Classifier: Programming Language :: Python :: 3.4
Classifier: Programming Language :: Python :: 3.5
Classifier: Topic :: Software Development :: Embedded Systems
Classifier: Topic :: Software Development :: Libraries :: Python Modules
